aett/__init__.py
aett/domain/__init__.py
aett/domain/aggregate.py
aett/domain/aggregate_repository.py
aett/domain/async_aggregate_repository.py
aett/domain/async_default_aggregate_repository.py
aett/domain/async_default_saga_repository.py
aett/domain/async_saga_repository.py
aett/domain/conflict_delegate.py
aett/domain/conflict_detector.py
aett/domain/conflicting_commit_exception.py
aett/domain/constants.py
aett/domain/default_aggregate_repository.py
aett/domain/default_saga_repository.py
aett/domain/duplicate_commit_exception.py
aett/domain/non_conflicting_commit_exception.py
aett/domain/py.typed
aett/domain/saga.py
aett/domain/saga_repository.py
aett/eventstore/__init__.py
aett/eventstore/base_command.py
aett/eventstore/base_event.py
aett/eventstore/commit.py
aett/eventstore/constants.py
aett/eventstore/domain_event.py
aett/eventstore/event_message.py
aett/eventstore/i_access_snapshots.py
aett/eventstore/i_access_snapshots_async.py
aett/eventstore/i_commit_events.py
aett/eventstore/i_commit_events_async.py
aett/eventstore/i_manage_persistence.py
aett/eventstore/i_manage_persistence_async.py
aett/eventstore/memento.py
aett/eventstore/py.typed
aett/eventstore/snapshot.py
aett/eventstore/stream_head.py
aett/eventstore/topic.py
aett/eventstore/topic_map.py
aett/py.typed
aett/storage/asynchronous/dynamodb/__init__.py
aett/storage/asynchronous/dynamodb/async_commit_store.py
aett/storage/asynchronous/dynamodb/async_persistence_management.py
aett/storage/asynchronous/dynamodb/py.typed
aett/storage/asynchronous/dynamodb/snapshot_store.py
aett/storage/asynchronous/mongodb/__init__.py
aett/storage/asynchronous/mongodb/async_commit_store.py
aett/storage/asynchronous/mongodb/async_persistence_management.py
aett/storage/asynchronous/mongodb/async_snapshot_store.py
aett/storage/asynchronous/mongodb/mapping.py
aett/storage/asynchronous/mongodb/py.typed
aett/storage/asynchronous/mysql/__init__.py
aett/storage/asynchronous/mysql/async_commit_store.py
aett-3.3.1.dist-info/LICENSE
aett-3.3.1.dist-info/METADATA
aett-3.3.1.dist-info/WHEEL
aett-3.3.1.dist-info/RECORD
