Metadata-Version: 2.3
Name: aett
Version: 3.3.1
Summary: Event store for Python
License: MIT License
Keywords: events,event store,sqlite,postgresql,mysql,mongodb,dynamodb,s3,event sourcing
Author: Jacob Reimers
Author-email: pypi@reimers.io
Requires-Python: >=3.11,<4.0
Classifier: License :: OSI Approved :: MIT License
Classifier: Programming Language :: Python
Classifier: Programming Language :: Python :: 3
Classifier: Programming Language :: Python :: 3.11
Provides-Extra: dynamodb
Provides-Extra: dynamodb-async
Provides-Extra: mongodb
Provides-Extra: mysql
Provides-Extra: mysql-async
Provides-Extra: postgresql
Provides-Extra: postgresql-async
Provides-Extra: s3
Provides-Extra: s3-async
Provides-Extra: sqlite-async
Requires-Dist: aioboto3 (>=15.0) ; extra == "dynamodb-async"
Requires-Dist: aioboto3 (>=15.0) ; extra == "s3-async"
Requires-Dist: aiomysql (>=0.2,<1.0) ; extra == "mysql-async"
Requires-Dist: aiosqlite (>=0.21,<1.0) ; extra == "sqlite-async"
Requires-Dist: asyncpg (>=0.30,<1.0) ; extra == "postgresql-async"
Requires-Dist: boto3 (>=1.38,<2.0) ; extra == "dynamodb"
Requires-Dist: boto3 (>=1.38,<2.0) ; extra == "s3"
Requires-Dist: boto3-stubs[full] (>=1.38) ; extra == "dynamodb"
Requires-Dist: multipledispatch (>=1.0,<2.0)
Requires-Dist: psycopg (>=3.2,<4.0) ; extra == "postgresql"
Requires-Dist: psycopg-binary (>=3.2,<4.0) ; extra == "postgresql"
Requires-Dist: pydantic (>=2.11,<3.0)
Requires-Dist: pymongo (>=4.13,<5.0) ; extra == "mongodb"
Requires-Dist: pymysql (>=1.1,<2.0) ; extra == "mysql"
Project-URL: Homepage, https://github.com/jjrdk/aett
